telecms_django/__init__.py
telecms_django/apps.py
telecms_django/configuration.py
telecms_django/route_view.py
telecms_django/router.py
telecms_django/settings.py
telecms_django/urls.py
telecms_django/__pycache__/__init__.cpython-38.pyc
telecms_django/migrations/0001_initial.py
telecms_django/migrations/0002_auto_20181014_2002.py
telecms_django/migrations/0003_auto_20191007_2005.py
telecms_django/migrations/__init__.py
telecms_django-1.0.1.dist-info/LICENSE
telecms_django-1.0.1.dist-info/METADATA
telecms_django-1.0.1.dist-info/WHEEL
telecms_django-1.0.1.dist-info/top_level.txt
telecms_django-1.0.1.dist-info/RECORD
