Metadata-Version: 2.1
Name: telecms-django
Version: 1.0.1
Home-page: https://github.com/serviceexchange/telecms_bridge
Author: Billy Truong
Author-email: account@service.exchange
License: MIT
License-File: LICENSE
Requires-Dist: Django
Requires-Dist: requests
Requires-Dist: telecms-bridge-base (==1.0.1)
